planctl/__init__.py
planctl/cli.py
planctl-1.0.1.dist-info/licenses/LICENSE
planctl-1.0.1.dist-info/METADATA
planctl-1.0.1.dist-info/WHEEL
planctl-1.0.1.dist-info/entry_points.txt
planctl-1.0.1.dist-info/top_level.txt
planctl-1.0.1.dist-info/RECORD
